oldreality/__init__.py
oldreality/__main__.py
oldreality/arkanoid/__init__.py
oldreality/arkanoid/arkanoid.py
oldreality/configmodel/__init__.py
oldreality/configmodel/configmodel.py
oldreality/pong/__init__.py
oldreality/pong/pong.py
oldreality/tetris/__init__.py
oldreality/tetris/tetris.py
oldreality-0.0.2.dist-info/LICENSE
oldreality-0.0.2.dist-info/METADATA
oldreality-0.0.2.dist-info/WHEEL
oldreality-0.0.2.dist-info/top_level.txt
oldreality-0.0.2.dist-info/RECORD
