Metadata-Version: 2.1
Name: oldreality
Version: 0.0.2
Summary: Retro arcade games
Home-page: https://github.com/yayguy4618/OldReality
Author: yayguy4618
License: UNKNOWN
Platform: UNKNOWN
Classifier: Programming Language :: Python :: 3
Classifier: License :: OSI Approved :: MIT License
Classifier: Operating System :: OS Independent
Requires-Python: >=3.6
